{
    "title": "佛規諭錄14",
    "range_remark": "(全)",
    "questions": [
        {
            "id": 1,
            "order": 1,
            "type": 1,
            "stem": "自師尊開始，凡誠心修道者，渡___即能超拔一層父母",
            "answer": 0,
            "choices": [
                "(1)64眾",
                "(2)72眾",
                "(3)84眾"
            ]
        },
        {
            "id": 2,
            "order": 2,
            "type": 1,
            "stem": "黃鐘、太簇…無射，是",
            "answer": 2,
            "choices": [
                "(1)六音",
                "(2)六呂",
                "(3)六律"
            ]
        },
        {
            "id": 3,
            "order": 3,
            "type": 1,
            "stem": "堯帝、舜帝的大道理，若無用”  “的善政來推行就無法      把天下治理成安樂的太平盛世",
            "answer": 0,
            "choices": [
                "(1)仁愛",
                "(2)慈悲",
                "(3)博愛"
            ]
        },
        {
            "id": 4,
            "order": 4,
            "type": 1,
            "stem": "白陽修道者是",
            "answer": 2,
            "choices": [
                "(1)重聖輕凡",
                "(2)重凡輕聖",
                "(3)聖凡雙兼"
            ]
        },
        {
            "id": 5,
            "order": 5,
            "type": 1,
            "stem": "時至”  “纏身靈",
            "answer": 2,
            "choices": [
                "(1)冤親",
                "(2)冤孽",
                "(3)冤魂"
            ]
        },
        {
            "id": 6,
            "order": 6,
            "type": 1,
            "stem": "辦此天道”  “為重",
            "answer": 0,
            "choices": [
                "(1)和",
                "(2)規",
                "(3) 理"
            ]
        },
        {
            "id": 7,
            "order": 7,
            "type": 1,
            "stem": "修道者怒嗔未改，恐有”  “事難成",
            "answer": 2,
            "choices": [
                "(1)業力",
                "(2)冤愆",
                "(3)阻礙"
            ]
        },
        {
            "id": 8,
            "order": 8,
            "type": 1,
            "stem": "仙佛開沙所用之機筆，稱",
            "answer": 1,
            "choices": [
                "(1)硃筆",
                "(2)玉衡",
                "(3)開沙筆"
            ]
        },
        {
            "id": 9,
            "order": 9,
            "type": 1,
            "stem": "天地循轉出”  “",
            "answer": 0,
            "choices": [
                "(1)聖人",
                "(2)聖賢",
                "(3)良賢"
            ]
        },
        {
            "id": 10,
            "order": 10,
            "type": 1,
            "stem": "多因貪戀”  “自棄性命堪可憫",
            "answer": 1,
            "choices": [
                "(1)名與利",
                "(2)酒色財",
                "(3)情與愛"
            ]
        },
        {
            "id": 11,
            "order": 11,
            "type": 1,
            "stem": "頑童“  ”固執守",
            "answer": 1,
            "choices": [
                "(1)秉性",
                "(2)硬性",
                "(3)習性"
            ]
        },
        {
            "id": 12,
            "order": 12,
            "type": 1,
            "stem": "人才辦道__當曉，行持正義扶三春，退怠之心若起念，九玄七祖       墜沉淪",
            "answer": 2,
            "choices": [
                "(1)禮",
                "(2)義",
                "(3)規",
                "(4)理"
            ]
        },
        {
            "id": 13,
            "order": 13,
            "type": 1,
            "stem": "輕凡言之乃”  “",
            "answer": 1,
            "choices": [
                "(1)大事",
                "(2)小事",
                "(3)正事"
            ]
        },
        {
            "id": 14,
            "order": 14,
            "type": 1,
            "stem": "定下”  “堅心立",
            "answer": 0,
            "choices": [
                "(1) 大志",
                "(2)目標",
                "(3)方向"
            ]
        },
        {
            "id": 15,
            "order": 15,
            "type": 1,
            "stem": "事前有準備免得臨時來不及",
            "answer": 1,
            "choices": [
                "(1)居安思危",
                "(2) 未雨綢繆",
                "(3)防範未然"
            ]
        },
        {
            "id": 16,
            "order": 16,
            "type": 1,
            "stem": "惟重”  ”無二意，",
            "answer": 0,
            "choices": [
                "(1) 天命",
                "(2) 天道",
                "(3) 師命"
            ]
        },
        {
            "id": 17,
            "order": 17,
            "type": 1,
            "stem": "一元有幾會",
            "answer": 0,
            "choices": [
                "(1)十二",
                "(2) 二十四",
                "(3) 三十六"
            ]
        },
        {
            "id": 18,
            "order": 18,
            "type": 1,
            "stem": "雷霆是指",
            "answer": 1,
            "choices": [
                "(1) 雷聲很大",
                "(2) 洪大而急發的雷聲",
                "(3) 聲勢浩大"
            ]
        },
        {
            "id": 19,
            "order": 19,
            "type": 1,
            "stem": "明暗坦崎分清方，",
            "answer": 0,
            "choices": [
                "(1)行暗",
                "(2)行明",
                "(3)行事",
                "(4)行道  上天助其緣"
            ]
        },
        {
            "id": 20,
            "order": 20,
            "type": 1,
            "stem": "九玄子孫沾榮光，____盡實人怎謗",
            "answer": 0,
            "choices": [
                "(1)素位",
                "(2)素行",
                "(3)清白",
                "(4)行道"
            ]
        },
        {
            "id": 21,
            "order": 21,
            "type": 1,
            "stem": "行道”  “真中真",
            "answer": 1,
            "choices": [
                "(1)守規",
                "(2)悟徹",
                "(3)力行"
            ]
        },
        {
            "id": 22,
            "order": 22,
            "type": 1,
            "stem": "殊途同歸真本根，殊途同歸是語出",
            "answer": 2,
            "choices": [
                "(1)大學",
                "(2)論語",
                "(3)易經"
            ]
        },
        {
            "id": 23,
            "order": 23,
            "type": 1,
            "stem": "勤修“  “品蓮證",
            "answer": 0,
            "choices": [
                "(1)令德",
                "(2)美德",
                "(3)內德"
            ]
        },
        {
            "id": 24,
            "order": 24,
            "type": 1,
            "stem": "“  ”之後千門展",
            "answer": 2,
            "choices": [
                "(1)萬教",
                "(2)五教",
                "(3)三教"
            ]
        },
        {
            "id": 25,
            "order": 25,
            "type": 1,
            "stem": "“  “最難化",
            "answer": 2,
            "choices": [
                "(1)驕傲之心",
                "(2)槓高之心",
                "(3)剛愎之心"
            ]
        },
        {
            "id": 26,
            "order": 26,
            "type": 1,
            "stem": "不該用時勿”  “如珍珠般收藏牢",
            "answer": 2,
            "choices": [
                "(1) 浪費",
                "(2)粗心",
                "(3)大意"
            ]
        },
        {
            "id": 27,
            "order": 27,
            "type": 1,
            "stem": "累卵之急無恐惶，累卵之急是指",
            "answer": 0,
            "choices": [
                "(1)危險萬分",
                "(2)急著出生的魚卵",
                "(3)眾多的魚卵"
            ]
        },
        {
            "id": 28,
            "order": 28,
            "type": 1,
            "stem": "螳螂捕蟬是典出何處",
            "answer": 0,
            "choices": [
                "(1)莊子",
                "(2)詩經",
                "(3)尚書",
                "(4)孟子"
            ]
        },
        {
            "id": 29,
            "order": 29,
            "type": 1,
            "stem": "謹者說言必”  “",
            "answer": 0,
            "choices": [
                "(1)細思",
                "(2) 思慮",
                "(3)思量"
            ]
        },
        {
            "id": 30,
            "order": 30,
            "type": 1,
            "stem": "可言之語卻隱匿，此謂",
            "answer": 0,
            "choices": [
                "(1)失言",
                "(2)失信",
                "(3)失禮"
            ]
        }
    ]
}